HaThOr/Chemostats.py
HaThOr/Metabolisms.py
HaThOr/__init__.py
HaThOr/chem_helper.py
HaThOr/pH_mtn_gen.py
HabitabilityTheOry-0.0.4.dist-info/.ipynb_checkpoints/PKG-INFO-checkpoint
HabitabilityTheOry-0.0.4.dist-info/.ipynb_checkpoints/SOURCES-checkpoint.txt
HabitabilityTheOry-0.0.4.dist-info/.ipynb_checkpoints/dependency_links-checkpoint.txt
HabitabilityTheOry-0.0.4.dist-info/.ipynb_checkpoints/requires-checkpoint.txt
HabitabilityTheOry-0.0.4.dist-info/LICENSE
HabitabilityTheOry-0.0.4.dist-info/METADATA
HabitabilityTheOry-0.0.4.dist-info/WHEEL
HabitabilityTheOry-0.0.4.dist-info/top_level.txt
HabitabilityTheOry-0.0.4.dist-info/RECORD
