Metadata-Version: 2.1
Name: HabitabilityTheOry
Version: 0.0.4
Summary: This package contains some useful functions to assess habitability of Chemostat-like environments to energy-limited microbes.
Author-email: Antonin Affholder <aaffholder@arizona.edu>
Project-URL: Homepage, https://gitlab.com/antonin.affholder/HaThOr_pkg
Project-URL: Bug Tracker, https://gitlab.com/antonin.affholder/HaThOr_pkg/-/issues
Classifier: Programming Language :: Python :: 3
Classifier: License :: OSI Approved :: MIT License
Classifier: Operating System :: OS Independent
Requires-Python: >=3.7
License-File: LICENSE
Requires-Dist: numpy
Requires-Dist: scipy
Requires-Dist: pandas
